{"links":[{"source":"states","target":"united","cooc":233.9375},{"source":"de","target":"la","cooc":120.71875},{"source":"british","target":"mission","cooc":98.900390625},{"source":"italian","target":"american","cooc":92.369140625},{"source":"service","target":"strategic","cooc":87.9140625},{"source":"italian","target":"fascist","cooc":82.173828125},{"source":"trans","target":"siberian","cooc":72.98828125},{"source":"american","target":"british","cooc":68.98828125},{"source":"italian","target":"abroad","cooc":62.330078125},{"source":"american","target":"mission","cooc":59.65234375},{"source":"america","target":"south","cooc":58.052734375},{"source":"staff","target":"chief","cooc":56.546875},{"source":"officers","target":"strategic","cooc":55.20703125},{"source":"la","target":"en","cooc":48.736328125},{"source":"irish","target":"american","cooc":45.744140625},{"source":"africa","target":"north","cooc":45.64453125},{"source":"de","target":"lo","cooc":43.9453125},{"source":"report","target":"london","cooc":43.724609375},{"source":"italian","target":"argentina","cooc":40.837890625},{"source":"en","target":"el","cooc":40.51171875}]}